odoo/addons/sale_order_deliverable_rate/README.rst
odoo/addons/sale_order_deliverable_rate/__init__.py
odoo/addons/sale_order_deliverable_rate/__manifest__.py
odoo/addons/sale_order_deliverable_rate/data/decimal_precision.xml
odoo/addons/sale_order_deliverable_rate/i18n/fr.po
odoo/addons/sale_order_deliverable_rate/i18n/sale_order_deliverable_rate.pot
odoo/addons/sale_order_deliverable_rate/models/__init__.py
odoo/addons/sale_order_deliverable_rate/models/sale_order.py
odoo/addons/sale_order_deliverable_rate/models/sale_order_line.py
odoo/addons/sale_order_deliverable_rate/readme/CONFIGURE.rst
odoo/addons/sale_order_deliverable_rate/readme/CONTRIBUTORS.rst
odoo/addons/sale_order_deliverable_rate/readme/DESCRIPTION.rst
odoo/addons/sale_order_deliverable_rate/readme/USAGE.rst
odoo/addons/sale_order_deliverable_rate/static/description/icon.png
odoo/addons/sale_order_deliverable_rate/static/description/index.html
odoo/addons/sale_order_deliverable_rate/tests/__init__.py
odoo/addons/sale_order_deliverable_rate/tests/common.py
odoo/addons/sale_order_deliverable_rate/tests/test_sale_order.py
odoo/addons/sale_order_deliverable_rate/tests/test_sale_order_line.py
odoo/addons/sale_order_deliverable_rate/views/sale_order.xml
odoo13_addon_sale_order_deliverable_rate-13.0.1.0.1.dev5.dist-info/METADATA
odoo13_addon_sale_order_deliverable_rate-13.0.1.0.1.dev5.dist-info/WHEEL
odoo13_addon_sale_order_deliverable_rate-13.0.1.0.1.dev5.dist-info/top_level.txt
odoo13_addon_sale_order_deliverable_rate-13.0.1.0.1.dev5.dist-info/RECORD
